thumborawesomehttploader/__init__.py
thumborawesomehttploader-0.0.1.dist-info/LICENSE
thumborawesomehttploader-0.0.1.dist-info/METADATA
thumborawesomehttploader-0.0.1.dist-info/WHEEL
thumborawesomehttploader-0.0.1.dist-info/top_level.txt
thumborawesomehttploader-0.0.1.dist-info/RECORD
