Metadata-Version: 2.1
Name: thumborawesomehttploader
Version: 0.0.1
Summary: Thumbor Awesome HTTP loader
Home-page: UNKNOWN
Author: Alexandru Pinca
Author-email: github@alexandru-pinca.me
License: MIT
Platform: UNKNOWN
